opencc/__init__.py
opencc/py.typed
opencc/clib/__init__.py
opencc/clib/opencc_clib.cpython-311-x86_64-linux-gnu.so
opencc/clib/bin/opencc
opencc/clib/bin/opencc_dict
opencc/clib/bin/opencc_phrase_extract
opencc/clib/include/opencc/BinaryDict.hpp
opencc/clib/include/opencc/Common.hpp
opencc/clib/include/opencc/Config.hpp
opencc/clib/include/opencc/Conversion.hpp
opencc/clib/include/opencc/ConversionChain.hpp
opencc/clib/include/opencc/Converter.hpp
opencc/clib/include/opencc/DartsDict.hpp
opencc/clib/include/opencc/Dict.hpp
opencc/clib/include/opencc/DictConverter.hpp
opencc/clib/include/opencc/DictEntry.hpp
opencc/clib/include/opencc/DictGroup.hpp
opencc/clib/include/opencc/Exception.hpp
opencc/clib/include/opencc/Export.hpp
opencc/clib/include/opencc/Lexicon.hpp
opencc/clib/include/opencc/MarisaDict.hpp
opencc/clib/include/opencc/MaxMatchSegmentation.hpp
opencc/clib/include/opencc/Optional.hpp
opencc/clib/include/opencc/PhraseExtract.hpp
opencc/clib/include/opencc/Segmentation.hpp
opencc/clib/include/opencc/Segments.hpp
opencc/clib/include/opencc/SerializableDict.hpp
opencc/clib/include/opencc/SerializedValues.hpp
opencc/clib/include/opencc/SimpleConverter.hpp
opencc/clib/include/opencc/TextDict.hpp
opencc/clib/include/opencc/UTF8StringSlice.hpp
opencc/clib/include/opencc/UTF8Util.hpp
opencc/clib/include/opencc/opencc.h
opencc/clib/include/opencc/opencc_config.h
opencc/clib/lib/libmarisa.a
opencc/clib/lib/libopencc.a
opencc/clib/lib/cmake/opencc/OpenCCConfig.cmake
opencc/clib/lib/cmake/opencc/OpenCCConfigVersion.cmake
opencc/clib/lib/cmake/opencc/OpenCCTargets-release.cmake
opencc/clib/lib/cmake/opencc/OpenCCTargets.cmake
opencc/clib/lib/pkgconfig/opencc.pc
opencc/clib/share/opencc/HKVariants.ocd2
opencc/clib/share/opencc/HKVariantsRev.ocd2
opencc/clib/share/opencc/HKVariantsRevPhrases.ocd2
opencc/clib/share/opencc/JPShinjitaiCharacters.ocd2
opencc/clib/share/opencc/JPShinjitaiPhrases.ocd2
opencc/clib/share/opencc/JPVariants.ocd2
opencc-1.2.0.dist-info/licenses/AUTHORS
opencc-1.2.0.dist-info/licenses/LICENSE
opencc-1.2.0.dist-info/METADATA
opencc-1.2.0.dist-info/WHEEL
opencc-1.2.0.dist-info/top_level.txt
opencc-1.2.0.dist-info/RECORD
