Metadata-Version: 2.4
Name: OpenCC
Version: 1.2.0
Summary:  Conversion between Traditional and Simplified Chinese
Home-page: https://github.com/BYVoid/OpenCC
Author: Carbo Kuo, Peng Huang, Kefu Chai, LI Daobing, Asias, Peng Wu, Xiaojun Ma, 佛振
Author-email: byvoid@byvoid.com, shawn.p.huang@gmail.com, tchaikov@gmail.com, lidaobing@gmail.com, asias.hejun@gmail.com, alexepico@gmail.com, damage3025@gmail.com, chen.sst@gmail.com
License: Apache License 2.0
Keywords: opencc,convert,chinese
Classifier: Development Status :: 5 - Production/Stable
Classifier: Intended Audience :: Developers
Classifier: Intended Audience :: Science/Research
Classifier: Natural Language :: Chinese (Simplified)
Classifier: Natural Language :: Chinese (Traditional)
Classifier: Programming Language :: Python
Classifier: Programming Language :: Python :: 3
Classifier: License :: OSI Approved :: Apache Software License
Classifier: Topic :: Scientific/Engineering
Classifier: Topic :: Software Development
Classifier: Topic :: Software Development :: Libraries
Classifier: Topic :: Software Development :: Libraries :: Python Modules
Classifier: Topic :: Software Development :: Localization
Classifier: Topic :: Text Processing :: Linguistic
Classifier: Typing :: Typed
License-File: LICENSE
License-File: AUTHORS
Dynamic: author
Dynamic: author-email
Dynamic: classifier
Dynamic: description
Dynamic: description-content-type
Dynamic: home-page
Dynamic: keywords
Dynamic: license
Dynamic: license-file
Dynamic: summary
